{
  "schema_version": 1,
  "generated_at": "2026-02-28T02:13:24.542Z",
  "base": "HKD",
  "rates": {
    "JPY": {
      "mastercard": null,
      "visa": null,
      "reference": {
        "rate": 0.050137,
        "date": "2026-02-28",
        "source": "open.er-api"
      }
    },
    "KRW": {
      "mastercard": null,
      "visa": null,
      "reference": {
        "rate": 0.005431,
        "date": "2026-02-28",
        "source": "open.er-api"
      }
    },
    "THB": {
      "mastercard": null,
      "visa": null,
      "reference": {
        "rate": 0.251781,
        "date": "2026-02-28",
        "source": "open.er-api"
      }
    },
    "TWD": {
      "mastercard": null,
      "visa": null,
      "reference": {
        "rate": 0.24942,
        "date": "2026-02-28",
        "source": "open.er-api"
      }
    },
    "CNY": {
      "mastercard": null,
      "visa": null,
      "reference": {
        "rate": 1.138716,
        "date": "2026-02-28",
        "source": "open.er-api"
      }
    },
    "MOP": {
      "mastercard": null,
      "visa": null,
      "reference": {
        "rate": 0.970874,
        "date": "2026-02-28",
        "source": "open.er-api"
      }
    },
    "GBP": {
      "mastercard": null,
      "visa": null,
      "reference": {
        "rate": 10.541073,
        "date": "2026-02-28",
        "source": "open.er-api"
      }
    },
    "EUR": {
      "mastercard": null,
      "visa": null,
      "reference": {
        "rate": 9.240607,
        "date": "2026-02-28",
        "source": "open.er-api"
      }
    },
    "USD": {
      "mastercard": null,
      "visa": null,
      "reference": {
        "rate": 7.823135,
        "date": "2026-02-28",
        "source": "open.er-api"
      }
    },
    "SGD": {
      "mastercard": null,
      "visa": null,
      "reference": {
        "rate": 6.183986,
        "date": "2026-02-28",
        "source": "open.er-api"
      }
    },
    "AUD": {
      "mastercard": null,
      "visa": null,
      "reference": {
        "rate": 5.563035,
        "date": "2026-02-28",
        "source": "open.er-api"
      }
    },
    "CAD": {
      "mastercard": null,
      "visa": null,
      "reference": {
        "rate": 5.730955,
        "date": "2026-02-28",
        "source": "open.er-api"
      }
    },
    "NZD": {
      "mastercard": null,
      "visa": null,
      "reference": {
        "rate": 4.687617,
        "date": "2026-02-28",
        "source": "open.er-api"
      }
    },
    "CHF": {
      "mastercard": null,
      "visa": null,
      "reference": {
        "rate": 10.164564,
        "date": "2026-02-28",
        "source": "open.er-api"
      }
    },
    "SEK": {
      "mastercard": null,
      "visa": null,
      "reference": {
        "rate": 0.865836,
        "date": "2026-02-28",
        "source": "open.er-api"
      }
    },
    "NOK": {
      "mastercard": null,
      "visa": null,
      "reference": {
        "rate": 0.822168,
        "date": "2026-02-28",
        "source": "open.er-api"
      }
    },
    "DKK": {
      "mastercard": null,
      "visa": null,
      "reference": {
        "rate": 1.238628,
        "date": "2026-02-28",
        "source": "open.er-api"
      }
    }
  }
}
